Metadata-Version: 2.1
Name: BluetoothLEpkgaiqi
Version: 1.0.1
Summary: A BluetoothLE  in Windows 10 V2004
Home-page: https://www.python.org/
Author: liumingming
Author-email: 994505261@eqq.com
License: UNKNOWN
Platform: UNKNOWN
Classifier: Programming Language :: Python :: 3
Classifier: License :: OSI Approved :: MIT License
Classifier: Operating System :: OS Independent
